xesn/__init__.py
xesn/cost.py
xesn/driver.py
xesn/esn.py
xesn/io.py
xesn/lazyesn.py
xesn/matrix.py
xesn/optim.py
xesn/psd.py
xesn/timer.py
xesn/utils.py
xesn/xdata.py
xesn/test/__init__.py
xesn/test/config-eager.yaml
xesn/test/config-lazy.yaml
xesn/test/cost.py
xesn/test/driver.py
xesn/test/esn.py
xesn/test/lazy.py
xesn/test/matrix.py
xesn/test/optim.py
xesn/test/psd.py
xesn/test/xdata.py
xesn-0.2.2.dist-info/LICENSE
xesn-0.2.2.dist-info/METADATA
xesn-0.2.2.dist-info/WHEEL
xesn-0.2.2.dist-info/top_level.txt
xesn-0.2.2.dist-info/RECORD
