Metadata-Version: 2.1
Name: xesn
Version: 0.2.2
Summary: Echo State Networks powered by xarray
Author-email: Timothy Smith <smith.timothy.andrew@gmail.com>
License: Apache License
Project-URL: homepage, https://github.com/timothyas/xesn
Project-URL: source, https://github.com/timothyas/xesn
Project-URL: documentation, https://xesn.readthedocs.io/en/latest/
Requires-Python: >=3.9
License-File: LICENSE
Requires-Dist: numpy
Requires-Dist: scipy
Requires-Dist: xarray
Requires-Dist: dask[complete]
Requires-Dist: zarr
Requires-Dist: smt >=2.2.1
Requires-Dist: matplotlib
Provides-Extra: gpus
Requires-Dist: cupy ; extra == 'gpus'
Requires-Dist: cupy-xarray ; extra == 'gpus'
Provides-Extra: test
Requires-Dist: pytest ; extra == 'test'
Requires-Dist: coverage ; extra == 'test'
